{
  "topic": "Bay Area",
  "provider": "groq",
  "generatedAt": "2026-05-28T04:02:01.768Z",
  "pack": {
    "twitter_thread": [
      "Planning a trip to the Bay Area and wondering what to do",
      "The Bay Area Book Festival is happening in downtown Berkeley, a great spot to meet authors and like-minded people",
      "Downtown Berkeley is also home to the University of California, Berkeley, a hub for intellectual and cultural events",
      "If you're in the Bay Area this weekend, consider stopping by the festival to meet some amazing authors",
      "The Bay Area is known for its vibrant cultural scene, with numerous festivals and events happening throughout the year",
      "From literature to music, the Bay Area has something to offer for every interest",
      "Whether you're a local or just visiting, the Bay Area Book Festival is a great way to experience the community"
    ],
    "linkedin": "The Bay Area is a hub for cultural and intellectual events, with the Bay Area Book Festival being a prime example. Happening in downtown Berkeley, the festival brings together authors and like-minded individuals for a weekend of discussion and celebration. With the University of California, Berkeley nearby, the area is steeped in history and knowledge. If you're in the Bay Area, consider attending the festival to network with others and expand your horizons. The Bay Area's vibrant cultural scene has something to offer for every interest, making it an ideal destination for both locals and visitors.",
    "tiktok_hooks": [
      "What's happening in the Bay Area this weekend",
      "Book lovers, assemble in downtown Berkeley",
      "Discover the vibrant cultural scene of the Bay Area"
    ],
    "reddit_headline": "Bay Area residents, what's the best way to spend a weekend in the area"
  },
  "niche": "software",
  "slug": "bay-area-2026-05-28",
  "date": "2026-05-28"
}