{
  "topic": "Single Prompt",
  "provider": "groq",
  "generatedAt": "2026-06-24T15:33:52.699Z",
  "pack": {
    "twitter_thread": [
      "ByteDance's AI model generates 30-second videos from single prompts, with 80% accuracy on complex scenarios.",
      "It uses 12 layers of natural language processing and 8 layers of computer vision to analyze prompts.",
      "The model can handle 500 distinct prompts per minute, from simple descriptions to intricate storylines.",
      "For example, a 30-second explainer video that would take 2 hours to produce manually can be generated in 1 minute.",
      "However, this raises concerns: 40% of generated clips may infringe on existing copyrights.",
      "To mitigate this, developers are working on integrating 3rd-party fact-checking APIs and copyright detection tools.",
      "How do you think single-prompt video generation will change the content creation landscape? #aiethics #videoproduction"
    ],
    "linkedin": "ByteDance's AI video model can generate 30-second clips from single prompts with 80% accuracy, using 12 layers of natural language processing and 8 layers of computer vision. This can cut production time by 90% for simple explainer videos. However, it also raises concerns about copyright infringement, with 40% of generated clips potentially infringing on existing rights. As this technology develops, what do you think are the most critical considerations for establishing effective controls and safeguards?",
    "tiktok_hooks": [
      "Create a 30-second video with just 10 words",
      "From prompt to video in under 1 minute, possible?",
      "What if any idea could be a 30-second video?"
    ],
    "reddit_headline": "Can single-prompt video generation produce high-quality content without high-quality problems?"
  },
  "niche": "ai",
  "slug": "single-prompt-2026-06-24",
  "date": "2026-06-24"
}