{
  "pending": [
    {
      "keyword": "dc-metro",
      "niche": "software",
      "publishedAt": "2026-07-05T04:53:40.084Z"
    },
    {
      "keyword": "stuart-dunkel",
      "niche": "ai",
      "publishedAt": "2026-07-05T14:40:30.677Z"
    },
    {
      "keyword": "dust-bowl",
      "niche": "software",
      "publishedAt": "2026-07-06T05:07:42.208Z"
    },
    {
      "keyword": "jonas-vingegaard",
      "niche": "ai",
      "publishedAt": "2026-07-07T04:47:43.644Z"
    },
    {
      "keyword": "happy-dootsday",
      "niche": "software",
      "publishedAt": "2026-07-08T04:11:39.366Z"
    },
    {
      "keyword": "plankparakeetfoyer",
      "niche": "ai",
      "publishedAt": "2026-07-08T04:11:41.817Z"
    },
    {
      "keyword": "ubuntu-touch",
      "niche": "software",
      "publishedAt": "2026-07-08T15:19:11.702Z"
    },
    {
      "keyword": "hank-green",
      "niche": "ai",
      "publishedAt": "2026-07-08T17:19:23.051Z"
    },
    {
      "keyword": "taylor-lorenz",
      "niche": "ai",
      "publishedAt": "2026-07-08T17:19:25.903Z"
    },
    {
      "keyword": "gym-bro",
      "niche": "ai",
      "publishedAt": "2026-07-08T21:56:01.453Z"
    },
    {
      "keyword": "earth-tone",
      "niche": "ai",
      "publishedAt": "2026-07-08T21:56:04.290Z"
    },
    {
      "keyword": "brown-universityai",
      "niche": "ai",
      "publishedAt": "2026-07-09T04:49:01.532Z"
    },
    {
      "keyword": "cut-reliance",
      "niche": "ai",
      "publishedAt": "2026-07-09T15:54:38.038Z"
    },
    {
      "keyword": "ibm-software",
      "niche": "ai",
      "publishedAt": "2026-07-09T15:54:40.984Z"
    },
    {
      "keyword": "personal-finance",
      "niche": "finance",
      "publishedAt": "2026-07-09T15:54:44.156Z"
    }
  ]
}