{
  "runs": 67,
  "lastRun": "2026-06-07T05:19:28.674Z",
  "streams": {
    "trend-signals": {
      "lastRunAt": "2026-06-07T05:19:31.008Z",
      "lastResult": "25 items / 20 topics / 8 opps",
      "totalRuns": 56
    },
    "affiliate-content": {
      "lastRunAt": "2026-06-07T05:19:40.930Z",
      "lastResult": "3 articles",
      "totalRuns": 56
    },
    "digital-products": {
      "lastRunAt": "2026-06-07T05:19:51.984Z",
      "lastResult": "1 products",
      "totalRuns": 57
    },
    "viral-factory": {
      "lastRunAt": "2026-06-07T05:20:23.580Z",
      "lastResult": "3 content packs",
      "totalRuns": 57
    },
    "x-publisher": {
      "lastRunAt": "2026-06-07T05:20:37.549Z",
      "lastResult": "posted 1 thread(s)",
      "totalRuns": 42
    },
    "mastodon-publisher": {
      "lastRunAt": "2026-06-07T05:20:37.560Z",
      "lastResult": "nothing to post",
      "totalRuns": 40
    },
    "bluesky-publisher": {
      "lastRunAt": "2026-06-07T05:20:45.903Z",
      "lastResult": "posted 1 thread(s)",
      "totalRuns": 40
    },
    "stripe-lister": {
      "lastRunAt": "2026-06-07T05:19:52.906Z",
      "lastResult": "listed 1, backfilled 0",
      "totalRuns": 41
    }
  },
  "totals": {
    "posts": 0,
    "products": 0,
    "signals": 0
  }
}