{
  "runs": 125,
  "lastRun": "2026-06-21T17:18:35.930Z",
  "streams": {
    "trend-signals": {
      "lastRunAt": "2026-06-21T17:18:38.392Z",
      "lastResult": "25 items / 20 topics / 8 opps",
      "totalRuns": 114
    },
    "affiliate-content": {
      "lastRunAt": "2026-06-21T17:18:47.640Z",
      "lastResult": "3 articles",
      "totalRuns": 114
    },
    "digital-products": {
      "lastRunAt": "2026-06-21T17:18:56.902Z",
      "lastResult": "1 products",
      "totalRuns": 115
    },
    "viral-factory": {
      "lastRunAt": "2026-06-21T17:19:55.262Z",
      "lastResult": "3 content packs",
      "totalRuns": 115
    },
    "x-publisher": {
      "lastRunAt": "2026-06-21T17:19:55.375Z",
      "lastResult": "nothing to post",
      "totalRuns": 100
    },
    "mastodon-publisher": {
      "lastRunAt": "2026-06-21T17:19:55.385Z",
      "lastResult": "nothing to post",
      "totalRuns": 98
    },
    "bluesky-publisher": {
      "lastRunAt": "2026-06-21T17:20:06.177Z",
      "lastResult": "posted 1 thread(s)",
      "totalRuns": 98
    },
    "stripe-lister": {
      "lastRunAt": "2026-06-21T17:18:57.655Z",
      "lastResult": "listed 1, backfilled 0",
      "totalRuns": 99
    }
  },
  "totals": {
    "posts": 0,
    "products": 0,
    "signals": 0
  }
}